syreal/Systems.py
syreal/__init__.py
syreal/__main__.py
syreal/myutilities.py
syreal-0.1.0.dist-info/METADATA
syreal-0.1.0.dist-info/WHEEL
syreal-0.1.0.dist-info/RECORD
